{"basic_csapp_floating-point.md":"51f57142","basic_network_stack.md":"1667fe87","code_algorithm_divide-and-conquer.md":"a06098f8","basic_index.md":"295a271b","basic_misc_index.md":"39521a29","basic_iq_3.md":"61ac87d2","basic_misc_type-category.md":"fd638f86","basic_misc_utf-8.md":"c2d06e72","basic_network_commands.md":"36dc7e4a","basic_network_dns.md":"f041d9e4","basic_os_ipc.md":"c90baa8d","code_algorithm_bfs.md":"3326bc80","code_algorithm_binary-search.md":"7e68fde1","code_algorithm_bit-operation.md":"54bde987","basic_db_sql-nosql.md":"709e3977","basic_network_tcp-udp-diff.md":"f4821127","basic_design-pattern_overview.md":"9525f7cb","basic_os_process-thread.md":"6eda6f03","basic_iq_1.md":"e6ae4517","code_algorithm_count-plane.md":"2c1a131c","basic_iq_2.md":"f176c819","code_algorithm_double-pointer.md":"f29428a6","basic_os_memory-management.md":"46ed29f1","basic_os_process-scheduling.md":"ca9eac3a","code_algorithm_dfs.md":"ae84a3e2","basic_os_thread-communication.md":"fbce147e","basic_network_udp.md":"23e596d7","basic_network_tcp.md":"394d3925","code_ds_trie.md":"556dd440","code_fe_alert-input.md":"d24fcedc","code_fe_array-flat.md":"e86e60bf","code_fe_async-serial-execution.md":"d40783f2","code_fe_bind.md":"7fdd7755","code_fe_class-extends.md":"bbebead7","code_fe_clone-deep.md":"0e05f05a","code_fe_concurrent-requests.md":"dd8785d0","code_fe_copy.md":"96d15345","code_fe_currying.md":"10a57ee5","code_fe_debounce-throttle.md":"0204390b","code_fe_detect-object-cycle.md":"97eed1e7","code_fe_dom-to-object.md":"e30f2d96","code_fe_eventbus.md":"7637cb68","code_fe_hierarchy.md":"ca667f73","code_fe_json-node-path.md":"49f80402","code_fe_new.md":"cc41f485","code_fe_promise-static.md":"d9413339","code_fe_promise.md":"9ed6bce9","code_fe_setinterval.md":"18dba92b","code_fe_slideshow.md":"a3ea95a7","code_fe_sorted-array-unique.md":"9b6041ef","code_index.md":"7bb0828e","fe_browser_after-input-url.md":"e0488988","fe_browser_cookie.md":"bc768987","fe_browser_cross-origin.md":"1561b9a5","fe_browser_drag.md":"1a112c3c","fe_browser_localstorage.md":"535a1c8d","fe_browser_reflow-repaint.md":"c430a9a8","fe_browser_service-worker.md":"6b8fdafd","fe_browser_tab-communication.md":"f825a37f","fe_css_animation.md":"d9f7f7e1","fe_css_bfc-ifc.md":"c864f6f1","fe_css_box-model.md":"a412d33e","fe_css_calc.md":"d5668e94","fe_css_center.md":"3f4b0215","fe_css_flex.md":"a3b78fce","fe_css_grid.md":"43f93613","fe_css_hide.md":"31bb592f","fe_css_position.md":"272c325f","fe_css_priority.md":"6805b3a9","fe_css_responsive.md":"67a3add5","fe_css_selector.md":"d1730ac0","fe_css_shape.md":"86120762","fe_css_table.md":"6a7fee25","fe_css_text-overflow.md":"03c76a2e","fe_css_three-column.md":"5f67b4e6","fe_css_top-middle-bottom.md":"fa573c65","fe_css_transform.md":"503eb4a1","fe_css_unit.md":"506b9465","fe_design_cdn.md":"ad23b9c8","fe_design_high-concurrency.md":"c7b9577f","fe_html_svg.md":"5df2db1c","fe_design_image-loading.md":"1beb996a","fe_design_pattern.md":"86444954","fe_design_perf.md":"fba2be9e","fe_design_web-vitals.md":"4009c49d","fe_devops_deploy.md":"7883164a","fe_html_iframe.md":"c6c87287","fe_browser_cors.md":"e474ab7f","fe_css_css-3.md":"26f2435c","fe_http_cache.md":"0dac1187","fe_http_https.md":"bb1199b5","fe_http_message.md":"763b1cfd","fe_http_method.md":"e830e375","fe_http_status-code.md":"f8fa1104","fe_index.md":"6ac16ad7","fe_js_arrow.md":"5be4955d","fe_js_check-type.md":"48fdb3a2","fe_js_promise.md":"f08aeab3","fe_js_prototype.md":"79ba2d1a","fe_js_set.md":"b6960882","fe_js_symbol.md":"31190131","fe_js_this.md":"e50b08af","fe_js_type-conversion.md":"10ad20e7","fe_js_websocket.md":"07d07011","fe_js_timsort.md":"ca863579","fe_js_xhr.md":"37d79e10","fe_security_session.md":"64bdd04d","fe_react_lifecycle.md":"6e5de4bf","fe_react_react-router.md":"37ff277a","fe_react_react-vs-vue.md":"04972a6d","fe_security_encryption.md":"a29fe26c","fe_js_class.md":"d2a723a8","fe_security_jwt.md":"3c8264ef","fe_react_component.md":"5d3a4f4e","fe_react_hooks.md":"94c32209","fe_react_build-your-own-react.md":"5c15771e","fe_js_closure.md":"ad534b93","fe_js_code.md":"cb4db021","fe_js_comparison.md":"32bb8f7a","fe_js_data-type.md":"22f3f3cf","fe_js_es6.md":"331a1e50","fe_js_event-loop.md":"fc59a3ee","fe_js_fetch.md":"98ccde4e","fe_js_inheritance.md":"c5cf6c86","fe_js_iterable.md":"bda688c6","fe_js_let-const.md":"23b5be29","fe_js_map.md":"8244077e","fe_js_number.md":"8c0bc522","fe_js_object.md":"a789d9a7","fe_security_token.md":"69b8e83c","fe_ts_keyof.md":"5297ef90","fe_ts_never.md":"699f8081","fe_ts_thistype.md":"499ab730","fe_security_web.md":"7bcbe451","fe_vite_build-tool.md":"4839baf5","fe_vite_intro.md":"a5e11011","fe_vue-router_history-mode.md":"00a11816","fe_vue-router_implementation.md":"8c49b52e","fe_vite_arch.md":"049ef220","fe_vue-router_window-history.md":"bdd2bc82","fe_design_iaas-paas-saas.md":"3d573b43","fe_vue-router_window-location.md":"660e63b2","code_ds_string.md":"8a07dde2","fe_vue_built-in-directives.md":"75e523bf","fe_browser_event.md":"919497d7","fe_browser_indexeddb.md":"7813caea","fe_browser_event-delegation.md":"c87018c0","fe_design_rbac.md":"4640fb38","fe_http_headers.md":"197490d4","code_algorithm_excel.md":"1afd2e7c","code_algorithm_greedy.md":"10600b20","code_algorithm_index.md":"59a85cc1","code_algorithm_dp.md":"b7904204","code_algorithm_link-game.md":"ccc34af6","code_algorithm_math.md":"879f6def","code_algorithm_moore.md":"d27ed1c7","code_algorithm_nsum.md":"80c5088c","code_algorithm_pack.md":"63155ea0","code_algorithm_path-sum.md":"d783cf31","code_algorithm_presum.md":"92def77f","fe_js_ajax.md":"10d4e688","code_algorithm_lru.md":"938fc96f","code_algorithm_simulation.md":"f4ab25ae","code_algorithm_sliding-window.md":"79adc48b","code_algorithm_sort-based.md":"2c2be919","code_algorithm_sort.md":"9015d91b","code_algorithm_stock.md":"005130e3","code_algorithm_topo-sort.md":"c1cb08ca","code_algorithm_trapping-rain.md":"c506b1c5","code_ds_array.md":"cb08b003","code_ds_avl.md":"72945050","code_ds_binary-tree-dfs.md":"0501d3aa","code_algorithm_rob.md":"cc197076","code_algorithm_quick-sort.md":"00bb6f9a","code_ds_binary-tree-level-order.md":"acfce45b","code_ds_binary-tree-traverse.md":"93c75325","fe_http_version.md":"ab0374ff","code_ds_bst.md":"6e7d3d6c","code_ds_hash-table.md":"32794613","code_ds_list.md":"4e659706","code_ds_binary-tree-recursive.md":"f0b300cb","code_ds_stack.md":"e80ce3a5","fe_vue_code.md":"e7c157ab","fe_vue_communication.md":"8effaac3","fe_vue_compile.md":"835e86c1","fe_vue_computed.md":"863994f9","fe_vue_defineproperty.md":"0d2bdc26","fe_vue_dependency-injection.md":"ad317fd7","fe_vue_dynamic-component.md":"bc31e83d","fe_js_array.md":"c0f0df00","fe_html_semantics.md":"3a605f17","fe_vue_first-paint.md":"98b9d170","fe_vue_internal-methods.md":"9302f544","fe_vue_lifecycle.md":"ede118d6","fe_vue_nexttick.md":"396b9400","fe_vue_object-reactivity.md":"b7ba2979","fe_vue_proxy.md":"392cde96","code_ds_monotonic-queue.md":"45b657d2","code_ds_monotonic-stack.md":"591b36a8","fe_vue_reactive-array.md":"cc2b449b","fe_vue_reactive-object.md":"a0b52344","fe_vue_reactive-primitive.md":"860d7297","fe_vue_reflect.md":"ed2d9e27","fe_vue_register-effect.md":"256ef7eb","fe_vue_render.md":"983f570d","fe_vue_slot.md":"451829bd","fe_vue_template-compile.md":"4caf2021","fe_vue_ts.md":"8a2e4374","fe_vue_watch.md":"5bb49219","fe_webpack_entry.md":"0e1a80fd","fe_webpack_overview.md":"c96b6054","fe_vue_reactive-collection.md":"7d1fa1e9","index.md":"03bddf6e","fe_js_bigint.md":"a9597ea7","fe_infra_bundler.md":"79a24883","fe_js_constructor.md":"8963c689"}
